spotled/__init__.py
spotled/fonts/4x6.yaff
spotled/fonts/5x7.yaff
spotled/fonts/5x8.yaff
spotled/fonts/6x10.yaff
spotled/fonts/6x12.yaff
spotled/fonts/6x9.yaff
spotled-1.3.0.dist-info/LICENSE
spotled-1.3.0.dist-info/METADATA
spotled-1.3.0.dist-info/WHEEL
spotled-1.3.0.dist-info/top_level.txt
spotled-1.3.0.dist-info/RECORD
