Metadata-Version: 2.1
Name: spotled
Version: 1.3.0
Summary: Allows control of SPOTLED bluetooth led displays via Python. (Unofficial)
Home-page: https://github.com/iwalton3/python-spotled
Author: Ian Walton
Author-email: ian@iwalton.com
License: MIT
Platform: UNKNOWN
Classifier: Programming Language :: Python :: 3
Classifier: License :: OSI Approved :: MIT License
Classifier: Operating System :: OS Independent
Requires-Python: >=3.7
Requires-Dist: gattlib
